ezLncPred/README.md
ezLncPred/__init__.py
ezLncPred/ezLncPred.py
ezLncPred/__pycache__/__init__.cpython-36.pyc
ezLncPred/__pycache__/ezLncPred.cpython-36.pyc
ezLncPred/__pycache__/parse.cpython-37.pyc
ezLncPred/__pycache__/tsvToJson.cpython-36.pyc
ezLncPred/__pycache__/tsvToJson.cpython-37.pyc
ezLncPred/docs/README_CNCI
ezLncPred/docs/README_CPAT
ezLncPred/docs/README_CPC2
ezLncPred/docs/README_CPPred
ezLncPred/docs/README_GFStack
ezLncPred/docs/README_LncADeep
ezLncPred/docs/README_PLEK
ezLncPred/docs/README_lgc
ezLncPred/docs/README_longdist
ezLncPred/models/__init__.py
ezLncPred/models/__init__.pyc
ezLncPred/models/CNCI/.CNCI.py.swp
ezLncPred/models/CNCI/.gitignore
ezLncPred/models/CNCI/CNCI.py
ezLncPred/models/CNCI/CNCI.pyc
ezLncPred/models/CNCI/LICENSE
ezLncPred/models/CNCI/__init__.py
ezLncPred/models/CNCI/__init__.pyc
ezLncPred/models/CNCI/gtf2Bed.pl
ezLncPred/models/CNCI/CNCI_Parameters/CNCI_matrix
ezLncPred/models/CNCI/CNCI_Parameters/plant.matrix
ezLncPred/models/CNCI/CNCI_Parameters/plant_model
ezLncPred/models/CNCI/CNCI_Parameters/plant_scale
ezLncPred/models/CNCI/CNCI_Parameters/python_model
ezLncPred/models/CNCI/CNCI_Parameters/python_scale
ezLncPred/models/CNCI/__pycache__/CNCI.cpython-36.pyc
ezLncPred/models/CNCI/__pycache__/__init__.cpython-36.pyc
ezLncPred/models/CPAT/.README.rst.swo
ezLncPred/models/CPAT/.README.rst.swp
ezLncPred/models/CPAT/LICENSE.txt
ezLncPred/models/CPAT/__init__.py
ezLncPred/models/CPAT/__init__.pyc
ezLncPred/models/CPAT/.eggs/README.txt
ezLncPred/models/CPAT/.eggs/nose-1.3.7-py2.7.egg/EGG-INFO/DESCRIPTION.rst
ezLncPred/models/CPAT/.eggs/nose-1.3.7-py2.7.egg/EGG-INFO/PKG-INFO
ezLncPred/models/CPAT/.eggs/nose-1.3.7-py2.7.egg/EGG-INFO/RECORD
ezLncPred/models/CPAT/.eggs/nose-1.3.7-py2.7.egg/EGG-INFO/WHEEL
ezLncPred/models/CPAT/.eggs/nose-1.3.7-py2.7.egg/EGG-INFO/entry_points.txt
ezLncPred/models/CPAT/.eggs/nose-1.3.7-py2.7.egg/EGG-INFO/metadata.json
ezLncPred/models/CPAT/.eggs/nose-1.3.7-py2.7.egg/EGG-INFO/top_level.txt
ezLncPred/models/CPAT/.eggs/nose-1.3.7-py2.7.egg/man/man1/nosetests.1
ezLncPred/models/CPAT/.eggs/nose-1.3.7-py2.7.egg/nose/__init__.py
ezLncPred/models/CPAT/.eggs/nose-1.3.7-py2.7.egg/nose/__main__.py
ezLncPred/models/CPAT/.eggs/nose-1.3.7-py2.7.egg/nose/case.py
ezLncPred/models/CPAT/.eggs/nose-1.3.7-py2.7.egg/nose/commands.py
ezLncPred/models/CPAT/.eggs/nose-1.3.7-py2.7.egg/nose/config.py
ezLncPred/models/CPAT/.eggs/nose-1.3.7-py2.7.egg/nose/core.py
ezLncPred/models/CPAT/lib/CPAT.egg-info/PKG-INFO
ezLncPred/models/CPAT/lib/CPAT.egg-info/SOURCES.txt
ezLncPred/models/CPAT/lib/CPAT.egg-info/dependency_links.txt
ezLncPred/models/CPAT/lib/CPAT.egg-info/not-zip-safe
ezLncPred/models/CPAT/lib/CPAT.egg-info/requires.txt
ezLncPred/models/CPAT/lib/CPAT.egg-info/top_level.txt
ezLncPred-1.4.dist-info/LICENSE
ezLncPred-1.4.dist-info/METADATA
ezLncPred-1.4.dist-info/WHEEL
ezLncPred-1.4.dist-info/entry_points.txt
ezLncPred-1.4.dist-info/top_level.txt
ezLncPred-1.4.dist-info/RECORD
