Metadata-Version: 2.1
Name: ezLncPred
Version: 1.4
Summary: An integrated python package for lncRNA identification
Home-page: https://github.com/LittleHannah/ezLncPred
Author: Xiaohan Zhao, Shuai Liu, Weiyang Li, Guangzhan Zhang, Wen Zhang*
Author-email: hannah__zhao@outlook.com
License: MIT
Keywords: lncRNA,lncRNA identification
Platform: UNKNOWN
Classifier: Programming Language :: Python :: 3
Classifier: License :: OSI Approved :: MIT License
Classifier: Operating System :: OS Independent
Requires-Dist: Keras (==2.2.4)
Requires-Dist: biopython (==1.72)
Requires-Dist: colorama (==0.4.1)
Requires-Dist: docutils (==0.15.2)
Requires-Dist: joblib (==0.13.2)
Requires-Dist: matplotlib (==2.2.2)
Requires-Dist: nose (==1.3.7)
Requires-Dist: numpy (==1.15.4)
Requires-Dist: pandas (==0.24.0)
Requires-Dist: pyfiglet (==0.8.post1)
Requires-Dist: pysam (==0.15.2)
Requires-Dist: setuptools (==42.0.2)
Requires-Dist: scikit-learn (==0.21.2)
